kore_plugins_ini/__init__.py
kore_plugins_ini/ini.py
kore_plugins_ini/parsers.py
kore_plugins_ini-0.1.0.dist-info/DESCRIPTION.rst
kore_plugins_ini-0.1.0.dist-info/METADATA
kore_plugins_ini-0.1.0.dist-info/RECORD
kore_plugins_ini-0.1.0.dist-info/WHEEL
kore_plugins_ini-0.1.0.dist-info/entry_points.txt
kore_plugins_ini-0.1.0.dist-info/metadata.json
kore_plugins_ini-0.1.0.dist-info/top_level.txt
